{
    "id": 0,
    "name": "",
    "abilities": [
        {
            "id": 0,
            "name": "if-else Statement",
            "value": 0,
            "parents": []
        },
        {
            "id": 0,
            "name": "While Loops",
            "value": 0,
            "parents": []
        },
        {
            "id": 0,
            "name": "do-while Loops",
            "value": 0,
            "parents": []
        },
        {
            "id": 0,
            "name": "for Loops",
            "value": 0,
            "parents": []
        },
        {
            "id": 0,
            "name": "Range-based Loops",
            "value": 0,
            "parents": []
        },
        {
            "id": 0,
            "name": "break Statement",
            "value": 0,
            "parents": []
        },
        {
            "id": 0,
            "name": "continue Statement",
            "value": 0,
            "parents": []
        },
        {
            "id": 0,
            "name": "goto Statement",
            "value": 0,
            "parents": []
        },
        {
            "id": 0,
            "name": "switch Statements",
            "value": 0,
            "parents": []
        },



	]
}